MANIFEST.in
README.rst
setup.cfg
setup.py
lpl_funniest/__init__.py
lpl_funniest/command_line.py
lpl_funniest/text.py
lpl_funniest.egg-info/PKG-INFO
lpl_funniest.egg-info/SOURCES.txt
lpl_funniest.egg-info/dependency_links.txt
lpl_funniest.egg-info/entry_points.txt
lpl_funniest.egg-info/not-zip-safe
lpl_funniest.egg-info/requires.txt
lpl_funniest.egg-info/top_level.txt
lpl_funniest/english/__init__.py
lpl_funniest/english/joke1.py
lpl_funniest/english/joke2.py
lpl_funniest/entry/__init__.py
lpl_funniest/entry/entry.py
lpl_funniest/tests/__init__.py
lpl_funniest/tests/test_command_line.py
lpl_funniest/tests/test_joke.py