Metadata-Version: 1.1
Name: lpl-funniest
Version: 4.0
Summary: The funniest joke in the world
Home-page: http://github.com/xxxxx
Author: Peilun
Author-email: xxxxx@example.com
License: MIT
Keywords: funniest joke comedy flying circus
Platform: UNKNOWN
Classifier: Development Status :: 3 - Alpha
Classifier: License :: OSI Approved :: MIT License
Classifier: Programming Language :: Python :: 2.7
Classifier: Topic :: Text Processing :: Linguistic
